g42cloudsdkvpc/__init__.py
g42cloudsdkvpc/v2/__init__.py
g42cloudsdkvpc/v2/vpc_async_client.py
g42cloudsdkvpc/v2/vpc_client.py
g42cloudsdkvpc/v2/model/__init__.py
g42cloudsdkvpc/v2/model/accept_vpc_peering_request.py
g42cloudsdkvpc/v2/model/accept_vpc_peering_response.py
g42cloudsdkvpc/v2/model/allowed_address_pair.py
g42cloudsdkvpc/v2/model/asscoiate_req.py
g42cloudsdkvpc/v2/model/associate_route_table_and_subnet_req.py
g42cloudsdkvpc/v2/model/associate_route_table_request.py
g42cloudsdkvpc/v2/model/associate_route_table_response.py
g42cloudsdkvpc/v2/model/batch_create_subnet_tags_request.py
g42cloudsdkvpc/v2/model/batch_create_subnet_tags_request_body.py
g42cloudsdkvpc/v2/model/batch_create_subnet_tags_response.py
g42cloudsdkvpc/v2/model/batch_create_vpc_tags_request.py
g42cloudsdkvpc/v2/model/batch_create_vpc_tags_request_body.py
g42cloudsdkvpc/v2/model/batch_create_vpc_tags_response.py
g42cloudsdkvpc/v2/model/batch_delete_subnet_tags_request.py
g42cloudsdkvpc/v2/model/batch_delete_subnet_tags_request_body.py
g42cloudsdkvpc/v2/model/batch_delete_subnet_tags_response.py
g42cloudsdkvpc/v2/model/batch_delete_vpc_tags_request.py
g42cloudsdkvpc/v2/model/batch_delete_vpc_tags_request_body.py
g42cloudsdkvpc/v2/model/batch_delete_vpc_tags_response.py
g42cloudsdkvpc/v2/model/binding_vif_details.py
g42cloudsdkvpc/v2/model/create_port_option.py
g42cloudsdkvpc/v2/model/create_port_request.py
g42cloudsdkvpc/v2/model/create_port_request_body.py
g42cloudsdkvpc/v2/model/create_port_response.py
g42cloudsdkvpc/v2/model/create_privateip_option.py
g42cloudsdkvpc/v2/model/create_privateip_request.py
g42cloudsdkvpc/v2/model/create_privateip_request_body.py
g42cloudsdkvpc/v2/model/create_privateip_response.py
g42cloudsdkvpc/v2/model/create_route_table_req.py
g42cloudsdkvpc/v2/model/create_route_table_request.py
g42cloudsdkvpc/v2/model/create_route_table_response.py
g42cloudsdkvpc/v2/model/create_routetable_req_body.py
g42cloudsdkvpc/v2/model/create_security_group_option.py
g42cloudsdkvpc-0.0.10b0.dist-info/LICENSE
g42cloudsdkvpc-0.0.10b0.dist-info/METADATA
g42cloudsdkvpc-0.0.10b0.dist-info/WHEEL
g42cloudsdkvpc-0.0.10b0.dist-info/top_level.txt
g42cloudsdkvpc-0.0.10b0.dist-info/RECORD
